.gitignore
MANIFEST.in
README.txt
bootstrap.py
buildout.cfg
setup.py
collective/__init__.py
collective.portlet.globalnav.egg-info/PKG-INFO
collective.portlet.globalnav.egg-info/SOURCES.txt
collective.portlet.globalnav.egg-info/dependency_links.txt
collective.portlet.globalnav.egg-info/entry_points.txt
collective.portlet.globalnav.egg-info/namespace_packages.txt
collective.portlet.globalnav.egg-info/not-zip-safe
collective.portlet.globalnav.egg-info/requires.txt
collective.portlet.globalnav.egg-info/top_level.txt
collective/portlet/__init__.py
collective/portlet/globalnav/__init__.py
collective/portlet/globalnav/configure.zcml
collective/portlet/globalnav/globalnavigationportlet.pt
collective/portlet/globalnav/globalnavigationportlet.py
collective/portlet/globalnav/version.txt
collective/portlet/globalnav/profiles/default/metadata.xml
collective/portlet/globalnav/profiles/default/portlets.xml
collective/portlet/globalnav/tests/__init__.py
collective/portlet/globalnav/tests/base.py
collective/portlet/globalnav/tests/test_portlet.py
docs/HISTORY.txt
docs/INSTALL.txt
docs/LICENSE.GPL
docs/LICENSE.txt