Metadata-Version: 1.0
Name: collective.portlet.globalnav
Version: 1.0
Summary: GlobalNavigation portlet
Home-page: http://svn.plone.org/svn/collective/
Author: UNKNOWN
Author-email: UNKNOWN
License: GPL
Platform: UNKNOWN
Classifier: Framework :: Plone
Classifier: Programming Language :: Python
